hachi_nio.py
hachi_nio-0.0.4.dist-info/LICENSE
hachi_nio-0.0.4.dist-info/METADATA
hachi_nio-0.0.4.dist-info/WHEEL
hachi_nio-0.0.4.dist-info/top_level.txt
hachi_nio-0.0.4.dist-info/RECORD
