Metadata-Version: 2.1
Name: hachi_nio
Version: 0.0.4
Summary: Hachi NIO protocol lib for Python
Author: Irineu Antunes
Classifier: Programming Language :: Python :: 3
Classifier: License :: OSI Approved :: MIT License
Classifier: Operating System :: OS Independent
Requires-Python: >=3.6
License-File: LICENSE
